polyqent/CNF.py
polyqent/Coefficient.py
polyqent/Constant.py
polyqent/Constraint.py
polyqent/Convertor.py
polyqent/DNF.py
polyqent/Farkas.py
polyqent/Handelman.py
polyqent/Parser.py
polyqent/Polynomial.py
polyqent/PositiveModel.py
polyqent/Putinar.py
polyqent/Solver.py
polyqent/UnknownVariable.py
polyqent/__init__.py
polyqent/main.py
polyqent-0.0.15.dist-info/licenses/LICENSE
polyqent-0.0.15.dist-info/METADATA
polyqent-0.0.15.dist-info/WHEEL
polyqent-0.0.15.dist-info/top_level.txt
polyqent-0.0.15.dist-info/RECORD
